{"code": 200, "data": {"questionId": 1316, "questionType": 1, "typeName": "\u542c\u97f3\u8fa9\u8bcd", "occurrence": 141, "isOccur": 0, "collectColorType": null, "practiceCount": 1, "createTime": "2020-11-11T13:56:00.000+00:00", "isVip": "1", "probationTotalCount": 0, "userProbationCountLeft": 0, "questionStatus": null, "ownerFlag": null, "similarToQuestionIdList": null, "title": "\u9009\u62e9\u6b63\u786e\u7684\u82f1\u8bed\u5355\u8bcd", "duration": 90, "difficulty": 1, "difficultyName": "\u7b80\u5355\uff08100\u4ee5\u4e0b\uff09", "notice": null, "options": [{"title": "\u5355\u8bcd 1", "correct": 0, "voice": "https://cdn.51ddedu.com/voices/477106265982504968.mp3", "word": "", "usPhonetic": null, "ukPhonetic": null, "explains": null, "ukSpeech": null, "usSpeech": null}, {"title": "\u5355\u8bcd 2", "correct": 1, "voice": "https://cdn.51ddedu.com/voices/477106265982504969.mp3", "word": "last", "usPhonetic": "l\u00e6st", "ukPhonetic": "l\u0251\u02d0st", "explains": "[\"adj. \u6700\u540e\u7684\uff1b\u6700\u8fd1\u7684\uff0c\u4e0a\u4e00\u6b21\u7684\uff1b\u6700\u7ec8\u7684\uff1b\u6700\u4e0d\u53ef\u80fd\u7684\uff1b\u6700\u5dee\u7684\uff1b\u4ec5\u5b58\u7684\",\"adv. \u6700\u8fd1\uff0c\u4e0a\u6b21\uff1b\u6700\u540e\",\"pron. \u6700\u540e\u7684\u4eba\u6216\u4e8b\u7269\uff1b\u6700\u8fd1\u53d1\u751f\u7684\u4e8b\u60c5\uff1b\u6700\u7ec8\",\"v. \u6301\u7eed\uff1b\u6301\u4e45\uff1b\u7ee7\u7eed\u4efb\u804c\uff1b\u5b58\u6d3b\uff1b\uff08\u4f9b\u7ed9\u3001\u8d44\u6e90\uff09\u8db3\u591f\uff08\u67d0\u4eba\uff09\u7528\u4e00\u6bb5\u65f6\u95f4\",\"n. \u978b\u6966\uff1b\u672b\u5c3e\",\"n. (Last) \uff08\u7f8e\u3001\u5fb7\uff09\u62c9\u65af\u7279\uff08\u4eba\u540d\uff09\"]", "ukSpeech": "https://cdn.51ddedu.com/voices/480039775890313216.mp3", "usSpeech": "https://cdn.51ddedu.com/voices/480039775890313217.mp3"}, {"title": "\u5355\u8bcd 3", "correct": 0, "voice": "https://cdn.51ddedu.com/voices/477106265982504970.mp3", "word": "", "usPhonetic": null, "ukPhonetic": null, "explains": null, "ukSpeech": null, "usSpeech": null}, {"title": "\u5355\u8bcd 4", "correct": 0, "voice": "https://cdn.51ddedu.com/voices/477106265982504971.mp3", "word": "", "usPhonetic": null, "ukPhonetic": null, "explains": null, "ukSpeech": null, "usSpeech": null}, {"title": "\u5355\u8bcd 5", "correct": 1, "voice": "https://cdn.51ddedu.com/voices/477106265982504972.mp3", "word": "once", "usPhonetic": "w\u028cns", "ukPhonetic": "w\u028cns", "explains": "[\"adv. \u4e00\u6b21\uff1b\u66fe\u7ecf\",\"conj. \u4e00\u65e6\",\"n. \u4e00\u6b21\uff0c\u4e00\u56de\"]", "ukSpeech": "https://cdn.51ddedu.com/voices/480043632770945025.mp3", "usSpeech": "https://cdn.51ddedu.com/voices/480043632770945026.mp3"}, {"title": "\u5355\u8bcd 6", "correct": 1, "voice": "https://cdn.51ddedu.com/voices/477106265982504973.mp3", "word": "golden", "usPhonetic": "\u02c8\u0261o\u028ald\u0259n", "ukPhonetic": "\u02c8\u0261\u0259\u028ald\u0259n", "explains": "[\"adj. \u91d1\u8272\u7684\uff0c\u9ec4\u91d1\u822c\u7684\uff1b\u73cd\u8d35\u7684\uff1b\u91d1\u5236\u7684\",\"n. (Golden)\u4eba\u540d\uff1b(\u82f1\u3001\u6cd5\u3001\u7f57\u3001\u5fb7\u3001\u745e\u5178)\u6208\u5c14\u767b\"]", "ukSpeech": "https://cdn.51ddedu.com/voices/480039921919201284.mp3", "usSpeech": "https://cdn.51ddedu.com/voices/480039921919201285.mp3"}, {"title": "\u5355\u8bcd 7", "correct": 0, "voice": "https://cdn.51ddedu.com/voices/477106265982504974.mp3", "word": "", "usPhonetic": null, "ukPhonetic": null, "explains": null, "ukSpeech": null, "usSpeech": null}, {"title": "\u5355\u8bcd 8", "correct": 0, "voice": "https://cdn.51ddedu.com/voices/477106265982504975.mp3", "word": "", "usPhonetic": null, "ukPhonetic": null, "explains": null, "ukSpeech": null, "usSpeech": null}, {"title": "\u5355\u8bcd 9", "correct": 0, "voice": "https://cdn.51ddedu.com/voices/477106265982504976.mp3", "word": "", "usPhonetic": null, "ukPhonetic": null, "explains": null, "ukSpeech": null, "usSpeech": null}], "answer": "\u7b2c4\u4e2a\u542c\u8d77\u6765\u50cfshow, \u5176\u5b9e\u6700\u540e\u6709\u4e2am\u7684\u97f3\uff0c\u6240\u4ee5\u4e0d\u9009\u3002 \u7b2c7\u4e2a\u542c\u8d77\u6765\u50cfthirsty\uff0c\u4f46\u5176\u5b9e\u8bf4\u7684\u662ffristy\uff0c\u6240\u4ee5\u4e0d\u9009\u3002 \u7b2c8\u4e2a\u542c\u8d77\u6765\u50cfmature\uff0c\u4f46\u5176\u5b9e\u8bf4\u7684\u662fbatour\uff0c\u6240\u4ee5\u4e0d\u9009\u3002\uff08\u5916\u6559\u610f\u89c1\uff0c\u4f9b\u53c2\u8003\uff09"}, "msg": "\u8bf7\u6c42\u6210\u529f\uff01"}