{"code": 200, "data": {"questionId": 2798, "questionType": 1, "typeName": "\u542c\u97f3\u8fa9\u8bcd", "occurrence": 10, "isOccur": 0, "collectColorType": null, "practiceCount": 1, "createTime": "2020-11-12T14:38:00.000+00:00", "isVip": "1", "probationTotalCount": 0, "userProbationCountLeft": 0, "questionStatus": null, "ownerFlag": null, "similarToQuestionIdList": null, "title": "\u9009\u62e9\u6b63\u786e\u7684\u82f1\u8bed\u5355\u8bcd", "duration": 90, "difficulty": 2, "difficultyName": "\u4e00\u822c\uff08105~115\uff09", "notice": null, "options": [{"title": "\u5355\u8bcd 1", "correct": 1, "voice": "https://cdn.51ddedu.com/voices/477106789968515084.mp3", "word": "filthy", "usPhonetic": "\u02c8f\u026al\u03b8i", "ukPhonetic": "\u02c8f\u026al\u03b8i", "explains": "[\"adj. \u80ae\u810f\u7684\uff1b\u6c61\u79fd\u7684\uff1b\u7325\u4eb5\u7684\"]", "ukSpeech": "https://cdn.51ddedu.com/voices/480044040792838144.mp3", "usSpeech": "https://cdn.51ddedu.com/voices/480044040792838145.mp3"}, {"title": "\u5355\u8bcd 2", "correct": 0, "voice": "https://cdn.51ddedu.com/voices/477106789968515085.mp3", "word": "", "usPhonetic": null, "ukPhonetic": null, "explains": null, "ukSpeech": null, "usSpeech": null}, {"title": "\u5355\u8bcd 3", "correct": 0, "voice": "https://cdn.51ddedu.com/voices/477106789968515086.mp3", "word": "", "usPhonetic": null, "ukPhonetic": null, "explains": null, "ukSpeech": null, "usSpeech": null}, {"title": "\u5355\u8bcd 4", "correct": 0, "voice": "https://cdn.51ddedu.com/voices/477106789968515087.mp3", "word": "", "usPhonetic": null, "ukPhonetic": null, "explains": null, "ukSpeech": null, "usSpeech": null}, {"title": "\u5355\u8bcd 5", "correct": 0, "voice": "https://cdn.51ddedu.com/voices/477106794263482368.mp3", "word": "", "usPhonetic": null, "ukPhonetic": null, "explains": null, "ukSpeech": null, "usSpeech": null}, {"title": "\u5355\u8bcd 6", "correct": 1, "voice": "https://cdn.51ddedu.com/voices/477106794263482369.mp3", "word": "density", "usPhonetic": "\u02c8dens\u0259ti", "ukPhonetic": "\u02c8dens\u0259ti", "explains": "[\"n. \u5bc6\u5ea6\"]", "ukSpeech": "https://cdn.51ddedu.com/voices/480041596956446723.mp3", "usSpeech": "https://cdn.51ddedu.com/voices/480041596956446724.mp3"}, {"title": "\u5355\u8bcd 7", "correct": 0, "voice": "https://cdn.51ddedu.com/voices/477106794263482370.mp3", "word": "", "usPhonetic": null, "ukPhonetic": null, "explains": null, "ukSpeech": null, "usSpeech": null}, {"title": "\u5355\u8bcd 8", "correct": 1, "voice": "https://cdn.51ddedu.com/voices/477106794263482371.mp3", "word": "surgery", "usPhonetic": "\u02c8s\u025c\u02d0rd\u0292\u0259ri", "ukPhonetic": "\u02c8s\u025c\u02d0d\u0292\u0259ri", "explains": "[\"n. \u5916\u79d1\uff1b\u5916\u79d1\u624b\u672f\uff1b\u624b\u672f\u5ba4\uff1b\u8bca\u7597\u5ba4\"]", "ukSpeech": "https://cdn.51ddedu.com/voices/480039058630774785.mp3", "usSpeech": "https://cdn.51ddedu.com/voices/480039058630774786.mp3"}, {"title": "\u5355\u8bcd 9", "correct": 0, "voice": "https://cdn.51ddedu.com/voices/477106794263482372.mp3", "word": "", "usPhonetic": null, "ukPhonetic": null, "explains": null, "ukSpeech": null, "usSpeech": null}], "answer": "\u5355\u8bcd5\u542c\u8d77\u6765\u50cfwayside[\u02c8we\u026asa\u026ad] \u4f46\u97f3\u9891\u8bfb\u7684\u662f[wi\u02d0sa\u026ad] \u6240\u4ee5\u4e0d\u9009"}, "msg": "\u8bf7\u6c42\u6210\u529f\uff01"}