{"code": 200, "data": {"questionId": 4668, "questionType": 1, "typeName": "\u542c\u97f3\u8fa9\u8bcd", "occurrence": 3, "isOccur": 0, "collectColorType": null, "practiceCount": 0, "createTime": "2020-11-13T21:48:00.000+00:00", "isVip": "1", "probationTotalCount": 0, "userProbationCountLeft": 0, "questionStatus": null, "ownerFlag": null, "similarToQuestionIdList": null, "title": "\u9009\u62e9\u6b63\u786e\u7684\u82f1\u8bed\u5355\u8bcd", "duration": 90, "difficulty": 2, "difficultyName": "\u4e00\u822c\uff08105~115\uff09", "notice": null, "options": [{"title": "\u5355\u8bcd 1", "correct": 1, "voice": "https://cdn.51ddedu.com/voices/477107180810539015.mp3", "word": "creativity", "usPhonetic": "\u02cckri\u02d0e\u026a\u02c8t\u026av\u0259ti", "ukPhonetic": "\u02cckri\u02d0e\u026a\u02c8t\u026av\u0259ti", "explains": "[\"n. \u521b\u9020\u529b\uff1b\u521b\u9020\u6027\"]", "ukSpeech": "https://cdn.51ddedu.com/voices/480042928396308484.mp3", "usSpeech": "https://cdn.51ddedu.com/voices/480042928396308485.mp3"}, {"title": "\u5355\u8bcd 2", "correct": 0, "voice": "https://cdn.51ddedu.com/voices/477107180810539016.mp3", "word": "", "usPhonetic": null, "ukPhonetic": null, "explains": null, "ukSpeech": null, "usSpeech": null}, {"title": "\u5355\u8bcd 3", "correct": 0, "voice": "https://cdn.51ddedu.com/voices/477107180810539017.mp3", "word": "", "usPhonetic": null, "ukPhonetic": null, "explains": null, "ukSpeech": null, "usSpeech": null}, {"title": "\u5355\u8bcd 4", "correct": 0, "voice": "https://cdn.51ddedu.com/voices/477107180810539018.mp3", "word": "", "usPhonetic": null, "ukPhonetic": null, "explains": null, "ukSpeech": null, "usSpeech": null}, {"title": "\u5355\u8bcd 5", "correct": 1, "voice": "https://cdn.51ddedu.com/voices/477107180810539019.mp3", "word": "constant", "usPhonetic": "\u02c8k\u0251\u02d0nst\u0259nt", "ukPhonetic": "\u02c8k\u0252nst\u0259nt", "explains": "[\"adj. \u4e0d\u53d8\u7684\uff1b\u6052\u5b9a\u7684\uff1b\u7ecf\u5e38\u7684\",\"n. [\u6570] \u5e38\u6570\uff1b\u6052\u91cf\",\"n. (Constant)\u4eba\u540d\uff1b(\u5fb7)\u5eb7\u65af\u5766\u7279\"]", "ukSpeech": "https://cdn.51ddedu.com/voices/480043220454084612.mp3", "usSpeech": "https://cdn.51ddedu.com/voices/480043220454084613.mp3"}, {"title": "\u5355\u8bcd 6", "correct": 1, "voice": "https://cdn.51ddedu.com/voices/477107185105506304.mp3", "word": "zebra", "usPhonetic": "\u02c8zi\u02d0br\u0259", "ukPhonetic": "\u02c8zebr\u0259; \u02c8zi\u02d0br\u0259", "explains": "[\"n. [\u810a\u690e] \u6591\u9a6c\",\"adj. \u6709\u6591\u7eb9\u7684\"]", "ukSpeech": "https://cdn.51ddedu.com/voices/480043357893038080.mp3", "usSpeech": "https://cdn.51ddedu.com/voices/480043357893038081.mp3"}, {"title": "\u5355\u8bcd 7", "correct": 0, "voice": "https://cdn.51ddedu.com/voices/477107185105506305.mp3", "word": null, "usPhonetic": null, "ukPhonetic": null, "explains": null, "ukSpeech": null, "usSpeech": null}, {"title": "\u5355\u8bcd 8", "correct": 0, "voice": "https://cdn.51ddedu.com/voices/477107185105506306.mp3", "word": "", "usPhonetic": null, "ukPhonetic": null, "explains": null, "ukSpeech": null, "usSpeech": null}, {"title": "\u5355\u8bcd 9", "correct": 1, "voice": "https://cdn.51ddedu.com/voices/477107185105506307.mp3", "word": "dissatisfied", "usPhonetic": "d\u026as\u02c8s\u00e6t\u026asfa\u026ad,d\u026a\u02c8s\u00e6t\u026asfa\u026ad", "ukPhonetic": "d\u026as\u02c8s\u00e6t\u026asfa\u026ad; d\u026a\u02c8s\u00e6t\u026asfa\u026ad", "explains": "[\"adj. \u4e0d\u6ee1\u610f\u7684\uff1b\u4e0d\u9ad8\u5174\u7684\uff1b\u6d41\u9732\u4e0d\u6ee1\u7684\",\"v. \u4f7f\u4e0d\u6ee1\uff08dissatisfy\u7684\u8fc7\u53bb\u5f0f\u548c\u8fc7\u53bb\u5206\u8bcd\uff09\"]", "ukSpeech": "https://cdn.51ddedu.com/voices/480040952711352320.mp3", "usSpeech": "https://cdn.51ddedu.com/voices/480040952711352321.mp3"}], "answer": ""}, "msg": "\u8bf7\u6c42\u6210\u529f\uff01"}