{"code": 200, "data": {"questionId": 5625, "questionType": 1, "typeName": "\u542c\u97f3\u8fa9\u8bcd", "occurrence": 1, "isOccur": 0, "collectColorType": null, "practiceCount": 0, "createTime": "2022-02-07T08:02:14.161+00:00", "isVip": "1", "probationTotalCount": 0, "userProbationCountLeft": 0, "questionStatus": null, "ownerFlag": null, "similarToQuestionIdList": null, "title": "\u9009\u62e9\u6b63\u786e\u7684\u82f1\u8bed\u5355\u8bcd", "duration": 90, "difficulty": 1, "difficultyName": "\u7b80\u5355\uff08100\u4ee5\u4e0b\uff09", "notice": null, "options": [{"title": "\u5355\u8bcd 1", "correct": 0, "voice": "https://cdn.51ddedu.com/voices/556133556854726656.mp3", "word": "", "usPhonetic": null, "ukPhonetic": null, "explains": null, "ukSpeech": null, "usSpeech": null}, {"title": "\u5355\u8bcd 2", "correct": 1, "voice": "https://cdn.51ddedu.com/voices/556133556854726657.mp3", "word": "ambitious", "usPhonetic": "\u00e6m\u02c8b\u026a\u0283\u0259s", "ukPhonetic": "\u00e6m\u02c8b\u026a\u0283\u0259s", "explains": "[\"adj. \u6709\u62b1\u8d1f\u7684\uff0c\u91ce\u5fc3\u52c3\u52c3\u7684\uff1b\u8d39\u52b2\u7684\uff0c\u8270\u5de8\u7684\uff1b\u70ed\u671b\u7684\"]", "ukSpeech": "https://cdn.51ddedu.com/voices/557150257218072576.mp3", "usSpeech": "https://cdn.51ddedu.com/voices/557150257218072577.mp3"}, {"title": "\u5355\u8bcd 3", "correct": 0, "voice": "https://cdn.51ddedu.com/voices/556133556854726658.mp3", "word": "", "usPhonetic": null, "ukPhonetic": null, "explains": null, "ukSpeech": null, "usSpeech": null}, {"title": "\u5355\u8bcd 4", "correct": 1, "voice": "https://cdn.51ddedu.com/voices/556133556854726659.mp3", "word": "savings", "usPhonetic": "\u02c8se\u026av\u026a\u014bz", "ukPhonetic": "\u02c8se\u026av\u026a\u014bz", "explains": "[\"n. \u50a8\u84c4\uff1b\u5b58\u6b3e\uff1b\u6551\u52a9\uff1b\u8282\u7701\u7269\uff08saving \u7684\u590d\u6570\u5f62\u5f0f\uff09\"]", "ukSpeech": "https://cdn.51ddedu.com/voices/557150257218072578.mp3", "usSpeech": "https://cdn.51ddedu.com/voices/557150257218072579.mp3"}, {"title": "\u5355\u8bcd 5", "correct": 0, "voice": "https://cdn.51ddedu.com/voices/556133556854726660.mp3", "word": "", "usPhonetic": null, "ukPhonetic": null, "explains": null, "ukSpeech": null, "usSpeech": null}, {"title": "\u5355\u8bcd 6", "correct": 1, "voice": "https://cdn.51ddedu.com/voices/556133556854726661.mp3", "word": "noble", "usPhonetic": "\u02c8no\u028abl", "ukPhonetic": "\u02c8n\u0259\u028abl", "explains": "[\"adj. \u5d07\u9ad8\u7684\uff0c\u9ad8\u5c1a\u7684\uff1b\u5b8f\u4f1f\u7684\uff0c\u5353\u8d8a\u7684\uff1b\u8d35\u65cf\u7684\uff0c\u9ad8\u8d35\u7684\uff1b\u60f0\u6027\u7684\",\"n. \uff08\u65e7\u65f6\u7684\uff09\u8d35\u65cf\",\"\u3010\u540d\u3011 \uff08Noble\uff09\uff08\u82f1\u3001\u6cd5\u3001\u610f\uff09\u8bfa\u5e03\u5c14\uff0c\uff08\u897f\uff09\u8bfa\u592b\u83b1\uff0c\uff08\u963f\u62c9\u4f2f\uff09\u52aa\u5e03\u83b1\uff08\u4eba\u540d\uff09\"]", "ukSpeech": "https://cdn.51ddedu.com/voices/557150261513039872.mp3", "usSpeech": "https://cdn.51ddedu.com/voices/557150261513039873.mp3"}, {"title": "\u5355\u8bcd 7", "correct": 1, "voice": "https://cdn.51ddedu.com/voices/556133556854726662.mp3", "word": "eructation", "usPhonetic": "\u02cci\u02d0r\u028ck\u02c8te\u026a\u0283\u0259n", "ukPhonetic": "\u026ar\u028ck\u02c8te\u026a\u0283\u0259n", "explains": "[\"n. \u6253\u55dd\uff1b\u55b7\u51fa\uff0c\u55b7\u51fa\u7269\"]", "ukSpeech": "https://cdn.51ddedu.com/voices/557150265808007168.mp3", "usSpeech": "https://cdn.51ddedu.com/voices/557150265808007169.mp3"}, {"title": "\u5355\u8bcd 8", "correct": 1, "voice": "https://cdn.51ddedu.com/voices/556133556854726663.mp3", "word": "propose", "usPhonetic": "pr\u0259\u02c8po\u028az", "ukPhonetic": "pr\u0259\u02c8p\u0259\u028az", "explains": "[\"vt. \u5efa\u8bae\uff1b\u6253\u7b97\uff0c\u8ba1\u5212\uff1b\u6c42\u5a5a\",\"vi. \u5efa\u8bae\uff1b\u6c42\u5a5a\uff1b\u6253\u7b97\"]", "ukSpeech": "https://cdn.51ddedu.com/voices/480039264789204992.mp3", "usSpeech": "https://cdn.51ddedu.com/voices/480039264789204993.mp3"}, {"title": "\u5355\u8bcd 9", "correct": 1, "voice": "https://cdn.51ddedu.com/voices/556133556854726664.mp3", "word": "amuse", "usPhonetic": "\u0259\u02c8mju\u02d0z", "ukPhonetic": "\u0259\u02c8mju\u02d0z", "explains": "[\"vt. \u5a31\u4e50\uff1b\u6d88\u9063\uff1b\u4f7f\u53d1\u7b11\uff1b\u4f7f\u6109\u5feb\"]", "ukSpeech": "https://cdn.51ddedu.com/voices/480042829612060674.mp3", "usSpeech": "https://cdn.51ddedu.com/voices/480042829612060675.mp3"}], "answer": null}, "msg": "\u8bf7\u6c42\u6210\u529f\uff01"}