{"code": 200, "data": {"questionId": 1587, "questionType": 2, "typeName": "\u5355\u8bcd\u8fa8\u6790", "occurrence": 37, "isOccur": 0, "collectColorType": null, "practiceCount": 1, "createTime": "2020-11-11T18:27:00.000+00:00", "isVip": "1", "probationTotalCount": 0, "userProbationCountLeft": 0, "questionStatus": null, "ownerFlag": null, "similarToQuestionIdList": null, "title": "\u9009\u62e9\u6b63\u786e\u7684\u82f1\u8bed\u5355\u8bcd", "duration": 60, "difficulty": 2, "difficultyName": "\u4e00\u822c\uff08105~115\uff09", "options": [{"correct": 0, "word": "custure", "usPhonetic": null, "ukPhonetic": null, "explains": null, "ukSpeech": null, "usSpeech": null}, {"correct": 1, "word": "shield", "usPhonetic": "\u0283i\u02d0ld", "ukPhonetic": "\u0283i\u02d0ld", "explains": "[\"n. \u76fe\uff1b\u9632\u62a4\u7269\uff1b\u4fdd\u62a4\u8005\",\"vt. \u906e\u853d\uff1b\u5305\u5e87\uff1b\u907f\u5f00\uff1b\u4fdd\u536b\",\"vi. \u9632\u5fa1\uff1b\u8d77\u4fdd\u62a4\u4f5c\u7528\",\"n. \uff08Shield\uff09\uff08\u82f1\uff09\u5e0c\u5c14\u5fb7\uff08\u4eba\u540d\uff09\"]", "ukSpeech": "https://duolingo-prod.oss-cn-shanghai.aliyuncs.com/voices/480047833248960515.mp3", "usSpeech": "https://duolingo-prod.oss-cn-shanghai.aliyuncs.com/voices/480047833248960516.mp3"}, {"correct": 1, "word": "bland", "usPhonetic": "bl\u00e6nd", "ukPhonetic": "bl\u00e6nd", "explains": "[\"adj. \u4e4f\u5473\u7684\uff1b\u6e29\u548c\u7684\uff1b\u51b7\u6f20\u7684\",\"vt. \u4f7f\u2026\u53d8\u5f97\u6de1\u800c\u65e0\u5473\uff1b\u9664\u6389\u2026\u7684\u7279\u6027\",\"vi. \u53d8\u5f97\u5e73\u6de1\u65e0\u5947\uff1b\u4e27\u5931\u7279\u6027\",\"n. (Bland)\u4eba\u540d\uff1b(\u82f1)\u5e03\u5170\u5fb7\"]", "ukSpeech": "https://duolingo-prod.oss-cn-shanghai.aliyuncs.com/voices/480047652860334080.mp3", "usSpeech": "https://duolingo-prod.oss-cn-shanghai.aliyuncs.com/voices/480047652860334081.mp3"}, {"correct": 0, "word": "realeze", "usPhonetic": null, "ukPhonetic": null, "explains": null, "ukSpeech": null, "usSpeech": null}, {"correct": 0, "word": "baraching", "usPhonetic": null, "ukPhonetic": null, "explains": null, "ukSpeech": null, "usSpeech": null}, {"correct": 1, "word": "densely", "usPhonetic": "\u02c8densli", "ukPhonetic": "\u02c8densli", "explains": "[\"adv. \u6d53\u5bc6\u5730\uff1b\u5bc6\u96c6\u5730\"]", "ukSpeech": "https://duolingo-prod.oss-cn-shanghai.aliyuncs.com/voices/480049113149214723.mp3", "usSpeech": "https://duolingo-prod.oss-cn-shanghai.aliyuncs.com/voices/480049117444182016.mp3"}, {"correct": 1, "word": "military", "usPhonetic": "\u02c8m\u026al\u0259teri", "ukPhonetic": "\u02c8m\u026al\u0259tri", "explains": "[\"adj. \u519b\u4e8b\u7684\uff1b\u519b\u4eba\u7684\uff1b\u9002\u4e8e\u6218\u4e89\u7684\",\"n. \u519b\u961f\uff1b\u519b\u4eba\"]", "ukSpeech": "https://duolingo-prod.oss-cn-shanghai.aliyuncs.com/voices/480051720194363394.mp3", "usSpeech": "https://duolingo-prod.oss-cn-shanghai.aliyuncs.com/voices/480051720194363395.mp3"}, {"correct": 1, "word": "essence", "usPhonetic": "\u02c8esns", "ukPhonetic": "\u02c8esns", "explains": "[\"n. \u672c\u8d28\uff0c\u5b9e\u8d28\uff1b\u7cbe\u534e\uff1b\u9999\u7cbe\",\"n. (Essence)\u4eba\u540d\uff1b(\u82f1)\u57c3\u68ee\u4e1d\"]", "ukSpeech": "https://duolingo-prod.oss-cn-shanghai.aliyuncs.com/voices/480049070199541762.mp3", "usSpeech": "https://duolingo-prod.oss-cn-shanghai.aliyuncs.com/voices/480049070199541763.mp3"}, {"correct": 1, "word": "affection", "usPhonetic": "\u0259\u02c8fek\u0283n", "ukPhonetic": "\u0259\u02c8fek\u0283n", "explains": "[\"n. \u559c\u7231\uff0c\u611f\u60c5\uff1b\u5f71\u54cd\uff1b\u611f\u67d3\"]", "ukSpeech": "https://duolingo-prod.oss-cn-shanghai.aliyuncs.com/voices/480050405934370818.mp3", "usSpeech": "https://duolingo-prod.oss-cn-shanghai.aliyuncs.com/voices/480050405934370819.mp3"}, {"correct": 1, "word": "specifically", "usPhonetic": "sp\u0259\u02c8s\u026af\u026akli", "ukPhonetic": "sp\u0259\u02c8s\u026af\u026akli", "explains": "[\"adv. \u7279\u522b\u5730\uff1b\u660e\u786e\u5730\"]", "ukSpeech": "https://duolingo-prod.oss-cn-shanghai.aliyuncs.com/voices/534180338327367680.mp3", "usSpeech": "https://duolingo-prod.oss-cn-shanghai.aliyuncs.com/voices/480039930509135872.mp3"}, {"correct": 1, "word": "luxurious", "usPhonetic": "l\u028c\u0261\u02c8\u0292\u028ari\u0259s", "ukPhonetic": "l\u028c\u0261\u02c8\u0292\u028a\u0259ri\u0259s", "explains": "[\"adj. \u5962\u4f88\u7684\uff1b\u4e30\u5bcc\u7684\uff1b\u653e\u7eb5\u7684\uff1b\u7279\u7ea7\u7684\"]", "ukSpeech": "https://duolingo-prod.oss-cn-shanghai.aliyuncs.com/voices/480052252770308096.mp3", "usSpeech": "https://duolingo-prod.oss-cn-shanghai.aliyuncs.com/voices/480052252770308097.mp3"}, {"correct": 0, "word": "accipit", "usPhonetic": null, "ukPhonetic": null, "explains": null, "ukSpeech": null, "usSpeech": null}, {"correct": 0, "word": "misundern", "usPhonetic": null, "ukPhonetic": null, "explains": null, "ukSpeech": null, "usSpeech": null}, {"correct": 1, "word": "rebellion", "usPhonetic": "r\u026a\u02c8belj\u0259n", "ukPhonetic": "r\u026a\u02c8belj\u0259n", "explains": "[\"n. \u53db\u4e71\uff1b\u53cd\u6297\uff1b\u8c0b\u53cd\uff1b\u4e0d\u670d\u4ece\"]", "ukSpeech": "https://duolingo-prod.oss-cn-shanghai.aliyuncs.com/voices/480048335760134144.mp3", "usSpeech": "https://duolingo-prod.oss-cn-shanghai.aliyuncs.com/voices/480048335760134145.mp3"}, {"correct": 0, "word": "annumed", "usPhonetic": null, "ukPhonetic": null, "explains": null, "ukSpeech": null, "usSpeech": null}, {"correct": 0, "word": "minalyy", "usPhonetic": null, "ukPhonetic": null, "explains": null, "ukSpeech": null, "usSpeech": null}, {"correct": 0, "word": "dividit", "usPhonetic": null, "ukPhonetic": null, "explains": null, "ukSpeech": null, "usSpeech": null}, {"correct": 0, "word": "patsess", "usPhonetic": null, "ukPhonetic": null, "explains": null, "ukSpeech": null, "usSpeech": null}]}, "msg": "\u8bf7\u6c42\u6210\u529f\uff01"}