{"code": 200, "data": {"questionId": 2540, "questionType": 2, "typeName": "\u5355\u8bcd\u8fa8\u6790", "occurrence": 10, "isOccur": 0, "collectColorType": null, "practiceCount": 1, "createTime": "2020-11-12T10:20:00.000+00:00", "isVip": "1", "probationTotalCount": 0, "userProbationCountLeft": 0, "questionStatus": null, "ownerFlag": null, "similarToQuestionIdList": null, "title": "\u9009\u62e9\u6b63\u786e\u7684\u82f1\u8bed\u5355\u8bcd", "duration": 60, "difficulty": 2, "difficultyName": "\u4e00\u822c\uff08105~115\uff09", "options": [{"correct": 0, "word": "reberience", "usPhonetic": null, "ukPhonetic": null, "explains": null, "ukSpeech": null, "usSpeech": null}, {"correct": 1, "word": "spending", "usPhonetic": "\u02c8spend\u026a\u014b", "ukPhonetic": "\u02c8spend\u026a\u014b", "explains": "[\"n. \u82b1\u8d39\uff1b\u5f00\u9500\",\"v. \u82b1\u8d39\uff1b\u5ea6\u8fc7\uff08spend\u7684\u73b0\u5728\u5206\u8bcd\u5f62\u5f0f\uff09\"]", "ukSpeech": "https://duolingo-prod.oss-cn-shanghai.aliyuncs.com/voices/480045977823088640.mp3", "usSpeech": "https://duolingo-prod.oss-cn-shanghai.aliyuncs.com/voices/480045977823088641.mp3"}, {"correct": 1, "word": "equivalent", "usPhonetic": "\u026a\u02c8kw\u026av\u0259l\u0259nt", "ukPhonetic": "\u026a\u02c8kw\u026av\u0259l\u0259nt", "explains": "[\"adj. \uff08\u5728\u4ef7\u503c\u3001\u6570\u91cf\u7b49\u65b9\u9762\uff09\u76f8\u7b49\u7684\uff1b\u7b49\u4ef7\u7684\uff1b\u7b49\u6548\u7684\uff1b\u7b49\u91cf\u7684\uff1b\u540c\u610f\u4e49\u7684\",\"n. \u5bf9\u7b49\u7684\u4eba\uff08\u6216\u4e8b\u7269\uff09\uff1b\u5f53\u91cf\"]", "ukSpeech": "https://duolingo-prod.oss-cn-shanghai.aliyuncs.com/voices/480050551963258883.mp3", "usSpeech": "https://duolingo-prod.oss-cn-shanghai.aliyuncs.com/voices/480050556258226176.mp3"}, {"correct": 1, "word": "wink", "usPhonetic": "w\u026a\u014bk", "ukPhonetic": "w\u026a\u014bk", "explains": "[\"v. \u7728\u773c\uff1b\u4f7f\u773c\u8272\uff1b\u95ea\u70c1\",\"n. \u7728\u773c\uff1b\u4f7f\u773c\u8272\uff1b\u95ea\u70c1\uff1b\u77ac\u95f4\uff1b\u5c0f\u61a9\uff1b \u5f39\u5851\u6599\u7247\u6e38\u620f\u4e2d\u7528\u7684\u5851\u6599\u5706\u7247\",\"n. (Wink) \uff08\u7f8e\u3001\u5fb7\u3001\u82f1\u3001\u8377\u3001\u5df4\u3001\u52a0\u3001\u745e\uff09\u6e29\u514b\uff08\u4eba\u540d\uff09\"]", "ukSpeech": "https://duolingo-prod.oss-cn-shanghai.aliyuncs.com/voices/480045771664658433.mp3", "usSpeech": "https://duolingo-prod.oss-cn-shanghai.aliyuncs.com/voices/480045771664658434.mp3"}, {"correct": 1, "word": "reform", "usPhonetic": "r\u026a\u02c8f\u0254\u02d0rm", "ukPhonetic": "r\u026a\u02c8f\u0254\u02d0m", "explains": "[\"v. \u6539\u9769\uff0c\u9769\u65b0\uff1b\u91cd\u7ec4\uff1b\uff08\u4f7f\uff09\u6539\u8fc7\u81ea\u65b0\uff1b\uff08\u77f3\u6cb9\u70bc\u5236\uff09\u91cd\u6574\",\"n. \u6539\u9769\uff0c\u6539\u826f\uff1b\u6539\u6b63\",\"adj. \u6539\u9769\u7684\uff1b\u6539\u9769\u6559\u4f1a\u7684\"]", "ukSpeech": "https://duolingo-prod.oss-cn-shanghai.aliyuncs.com/voices/480046158211715073.mp3", "usSpeech": "https://duolingo-prod.oss-cn-shanghai.aliyuncs.com/voices/480046158211715074.mp3"}, {"correct": 0, "word": "flacturet", "usPhonetic": null, "ukPhonetic": null, "explains": null, "ukSpeech": null, "usSpeech": null}, {"correct": 0, "word": "soculty", "usPhonetic": null, "ukPhonetic": null, "explains": null, "ukSpeech": null, "usSpeech": null}, {"correct": 0, "word": "vacial", "usPhonetic": null, "ukPhonetic": null, "explains": null, "ukSpeech": null, "usSpeech": null}, {"correct": 0, "word": "therach", "usPhonetic": null, "ukPhonetic": null, "explains": null, "ukSpeech": null, "usSpeech": null}, {"correct": 0, "word": "compessed", "usPhonetic": null, "ukPhonetic": null, "explains": null, "ukSpeech": null, "usSpeech": null}, {"correct": 1, "word": "fluid", "usPhonetic": "\u02c8flu\u02d0\u026ad", "ukPhonetic": "\u02c8flu\u02d0\u026ad", "explains": "[\"n. \u6d41\u4f53\uff0c\u6db2\u4f53\",\"adj. \u6d41\u52a8\u7684\uff1b\u4e0d\u56fa\u5b9a\u7684\uff0c\u6613\u53d8\u7684\uff1b\u6d41\u7545\u7684\uff0c\u4f18\u7f8e\u7684\uff1b\u6db2\u538b\u4f20\u52a8\u7684\"]", "ukSpeech": "https://duolingo-prod.oss-cn-shanghai.aliyuncs.com/voices/480050594912931842.mp3", "usSpeech": "https://duolingo-prod.oss-cn-shanghai.aliyuncs.com/voices/480050594912931843.mp3"}, {"correct": 0, "word": "variabineed", "usPhonetic": null, "ukPhonetic": null, "explains": null, "ukSpeech": null, "usSpeech": null}, {"correct": 0, "word": "poace", "usPhonetic": null, "ukPhonetic": null, "explains": null, "ukSpeech": null, "usSpeech": null}, {"correct": 1, "word": "ounce", "usPhonetic": "a\u028ans", "ukPhonetic": "a\u028ans", "explains": "[\"n. \u76ce\u53f8\uff1b\u5c11\u91cf\uff1b\u96ea\u8c79\"]", "ukSpeech": "https://duolingo-prod.oss-cn-shanghai.aliyuncs.com/voices/480052300014948354.mp3", "usSpeech": "https://duolingo-prod.oss-cn-shanghai.aliyuncs.com/voices/480052300014948355.mp3"}, {"correct": 0, "word": "inspectly", "usPhonetic": null, "ukPhonetic": null, "explains": null, "ukSpeech": null, "usSpeech": null}, {"correct": 1, "word": "repetitive", "usPhonetic": "r\u026a\u02c8pet\u0259t\u026av", "ukPhonetic": "r\u026a\u02c8pet\u0259t\u026av", "explains": "[\"adj. \u91cd\u590d\u7684\"]", "ukSpeech": "https://duolingo-prod.oss-cn-shanghai.aliyuncs.com/voices/480049589890584580.mp3", "usSpeech": "https://duolingo-prod.oss-cn-shanghai.aliyuncs.com/voices/480049589890584581.mp3"}, {"correct": 0, "word": "spourden", "usPhonetic": null, "ukPhonetic": null, "explains": null, "ukSpeech": null, "usSpeech": null}, {"correct": 0, "word": "sketter", "usPhonetic": null, "ukPhonetic": null, "explains": null, "ukSpeech": null, "usSpeech": null}]}, "msg": "\u8bf7\u6c42\u6210\u529f\uff01"}