{"code": 200, "data": {"questionId": 2815, "questionType": 2, "typeName": "\u5355\u8bcd\u8fa8\u6790", "occurrence": 12, "isOccur": 0, "collectColorType": 3, "practiceCount": 2, "createTime": "2020-11-12T14:55:00.000+00:00", "isVip": "1", "probationTotalCount": 0, "userProbationCountLeft": 0, "questionStatus": null, "ownerFlag": null, "similarToQuestionIdList": null, "title": "\u9009\u62e9\u6b63\u786e\u7684\u82f1\u8bed\u5355\u8bcd", "duration": 60, "difficulty": 3, "difficultyName": "\u96be\uff08120\u4ee5\u4e0a\uff09", "options": [{"correct": 1, "word": "fabulous", "usPhonetic": "\u02c8f\u00e6bj\u0259l\u0259s", "ukPhonetic": "\u02c8f\u00e6bj\u0259l\u0259s", "explains": "[\"adj. \u96be\u4ee5\u7f6e\u4fe1\u7684\uff1b\u4f20\u8bf4\u7684\uff0c\u5bd3\u8a00\u4e2d\u7684\uff1b\u6781\u597d\u7684\"]", "ukSpeech": "https://duolingo-prod.oss-cn-shanghai.aliyuncs.com/voices/480049920603066369.mp3", "usSpeech": "https://duolingo-prod.oss-cn-shanghai.aliyuncs.com/voices/480049920603066370.mp3"}, {"correct": 1, "word": "modestly", "usPhonetic": "\u02c8m\u0251\u02d0d\u026astli", "ukPhonetic": "\u02c8m\u0252d\u026astli", "explains": "[\"adv. \u8c28\u614e\u5730\uff1b\u9002\u5f53\u5730\"]", "ukSpeech": "https://duolingo-prod.oss-cn-shanghai.aliyuncs.com/voices/480050904150577154.mp3", "usSpeech": "https://duolingo-prod.oss-cn-shanghai.aliyuncs.com/voices/480050904150577155.mp3"}, {"correct": 1, "word": "deprived", "usPhonetic": "d\u026a\u02c8pra\u026avd", "ukPhonetic": "d\u026a\u02c8pra\u026avd", "explains": "[\"adj. \u8d2b\u56f0\u7684\uff0c\u7a77\u82e6\u7684\uff0c\u4e25\u91cd\u532e\u4e4f\u7684\uff1b\uff08\u4eba\uff09\u4e27\u5931\u7684\uff0c\u88ab\u5265\u593a\u7684\"]", "ukSpeech": "https://duolingo-prod.oss-cn-shanghai.aliyuncs.com/voices/480051922057826304.mp3", "usSpeech": "https://duolingo-prod.oss-cn-shanghai.aliyuncs.com/voices/480051922057826305.mp3"}, {"correct": 0, "word": "wimpa", "usPhonetic": null, "ukPhonetic": null, "explains": null, "ukSpeech": null, "usSpeech": null}, {"correct": 1, "word": "shaken", "usPhonetic": "\u02c8\u0283e\u026ak\u0259n", "ukPhonetic": "\u02c8\u0283e\u026ak\u0259n", "explains": "[\"v. \u6447\u52a8\uff0c\u52a8\u6447\uff08shake\u7684\u8fc7\u53bb\u5206\u8bcd\uff09\",\"n. (Shaken)\u4eba\u540d\uff1b(\u4fc4)\u6c99\u80af\"]", "ukSpeech": "https://duolingo-prod.oss-cn-shanghai.aliyuncs.com/voices/480048980005228546.mp3", "usSpeech": "https://duolingo-prod.oss-cn-shanghai.aliyuncs.com/voices/480048980005228547.mp3"}, {"correct": 0, "word": "whoossibly", "usPhonetic": null, "ukPhonetic": null, "explains": null, "ukSpeech": null, "usSpeech": null}, {"correct": 1, "word": "newsletter", "usPhonetic": "\u02c8nu\u02d0zlet\u0259r", "ukPhonetic": "\u02c8nju\u02d0zlet\u0259(r)", "explains": "[\"n. \u65f6\u4e8b\u901a\u8baf\"]", "ukSpeech": "https://duolingo-prod.oss-cn-shanghai.aliyuncs.com/voices/480047734464712706.mp3", "usSpeech": "https://duolingo-prod.oss-cn-shanghai.aliyuncs.com/voices/480047734464712707.mp3"}, {"correct": 1, "word": "equation", "usPhonetic": "\u026a\u02c8kwe\u026a\u0292n", "ukPhonetic": "\u026a\u02c8kwe\u026a\u0292n", "explains": "[\"n. \u65b9\u7a0b\u5f0f\uff0c\u7b49\u5f0f\uff1b\u76f8\u7b49\uff1b[\u5316\u5b66] \u53cd\u5e94\u5f0f\"]", "ukSpeech": "https://duolingo-prod.oss-cn-shanghai.aliyuncs.com/voices/480048103831900160.mp3", "usSpeech": "https://duolingo-prod.oss-cn-shanghai.aliyuncs.com/voices/480048103831900161.mp3"}, {"correct": 1, "word": "sensibility", "usPhonetic": "\u02ccsens\u0259\u02c8b\u026al\u0259ti", "ukPhonetic": "\u02ccsens\u0259\u02c8b\u026al\u0259ti", "explains": "[\"n. \u60c5\u611f\uff1b\u654f\u611f\u6027\uff1b\u611f\u89c9\uff1b\u8bc6\u522b\u529b\"]", "ukSpeech": "https://duolingo-prod.oss-cn-shanghai.aliyuncs.com/voices/480047854723796994.mp3", "usSpeech": "https://duolingo-prod.oss-cn-shanghai.aliyuncs.com/voices/480047854723796995.mp3"}, {"correct": 1, "word": "dissertation", "usPhonetic": "\u02ccd\u026as\u0259r\u02c8te\u026a\u0283n", "ukPhonetic": "\u02ccd\u026as\u0259\u02c8te\u026a\u0283n", "explains": "[\"n. \u8bba\u6587\uff0c\u4e13\u9898\uff1b\u5b66\u672f\u6f14\u8bb2\"]", "ukSpeech": "https://duolingo-prod.oss-cn-shanghai.aliyuncs.com/voices/480046652132954113.mp3", "usSpeech": "https://duolingo-prod.oss-cn-shanghai.aliyuncs.com/voices/480046652132954114.mp3"}, {"correct": 0, "word": "cirit", "usPhonetic": null, "ukPhonetic": null, "explains": null, "ukSpeech": null, "usSpeech": null}, {"correct": 1, "word": "deodorant", "usPhonetic": "di\u02d0\u02c8o\u028ad\u0259r\u0259nt", "ukPhonetic": "di\u02d0\u02c8\u0259\u028ad\u0259r\u0259nt", "explains": "[\"n. \u9664\u81ed\u5242\uff0c\u4f53\u9999\u5242\",\"adj. \u9664\u81ed\u7684\uff0c\u9632\u81ed\u7684\"]", "ukSpeech": "https://duolingo-prod.oss-cn-shanghai.aliyuncs.com/voices/480050350099795968.mp3", "usSpeech": "https://duolingo-prod.oss-cn-shanghai.aliyuncs.com/voices/480050350099795969.mp3"}, {"correct": 1, "word": "initiative", "usPhonetic": "\u026a\u02c8n\u026a\u0283\u0259t\u026av", "ukPhonetic": "\u026a\u02c8n\u026a\u0283\u0259t\u026av", "explains": "[\"n. \u4e3b\u52a8\u6743\uff1b\u79ef\u6781\u6027\uff1b\u9996\u521b\u7cbe\u795e\uff1b\u65b0\u65b9\u6848\uff1b\u5021\u8bae\",\"adj. \u521d\u6b65\u7684\uff0c\u57fa\u7840\u7684\"]", "ukSpeech": "https://duolingo-prod.oss-cn-shanghai.aliyuncs.com/voices/480051415251685376.mp3", "usSpeech": "https://duolingo-prod.oss-cn-shanghai.aliyuncs.com/voices/480051415251685377.mp3"}, {"correct": 1, "word": "asset", "usPhonetic": "\u02c8\u00e6set", "ukPhonetic": "\u02c8\u00e6set", "explains": "[\"n. \u8d44\u4ea7\uff1b\u4f18\u70b9\uff1b\u6709\u7528\u7684\u4e1c\u897f\uff1b\u6709\u5229\u6761\u4ef6\uff1b\u8d22\u4ea7\uff1b\u6709\u4ef7\u503c\u7684\u4eba\u6216\u7269\",\"n. \uff08\u6cd5\uff09\u963f\u585e\uff08\u4eba\u540d\uff09\"]", "ukSpeech": "https://duolingo-prod.oss-cn-shanghai.aliyuncs.com/voices/480052072381681666.mp3", "usSpeech": "https://duolingo-prod.oss-cn-shanghai.aliyuncs.com/voices/480052072381681667.mp3"}, {"correct": 1, "word": "relieve", "usPhonetic": "r\u026a\u02c8li\u02d0v", "ukPhonetic": "r\u026a\u02c8li\u02d0v", "explains": "[\"vt. \u89e3\u9664\uff0c\u51cf\u8f7b\uff1b\u4f7f\u4e0d\u5355\u8c03\u4e4f\u5473\uff1b\u6362\u2026\u2026\u7684\u73ed\uff1b\u89e3\u56f4\uff1b\u4f7f\u653e\u5fc3\"]", "ukSpeech": "https://duolingo-prod.oss-cn-shanghai.aliyuncs.com/voices/480049671494963201.mp3", "usSpeech": "https://duolingo-prod.oss-cn-shanghai.aliyuncs.com/voices/480049671494963202.mp3"}, {"correct": 0, "word": "dorate", "usPhonetic": null, "ukPhonetic": null, "explains": null, "ukSpeech": null, "usSpeech": null}, {"correct": 1, "word": "overload", "usPhonetic": "\u02cco\u028av\u0259r\u02c8lo\u028ad", "ukPhonetic": "\u02cc\u0259\u028av\u0259\u02c8l\u0259\u028ad", "explains": "[\"v. \uff08\u4f7f\uff09\u8fc7\u8f7d\uff0c\u8d85\u8f7d\uff1b\uff08\u4f7f\uff09\u8d1f\u62c5\u8fc7\u91cd\uff1b\uff08\u4f7f\uff09\u7535\u529b\u7cfb\u7edf\u8d85\u8d1f\u8377\",\"n. \u8d85\u8f7d\u91cf\"]", "ukSpeech": "https://duolingo-prod.oss-cn-shanghai.aliyuncs.com/voices/480049027249868802.mp3", "usSpeech": "https://duolingo-prod.oss-cn-shanghai.aliyuncs.com/voices/480049027249868803.mp3"}, {"correct": 0, "word": "irise", "usPhonetic": null, "ukPhonetic": null, "explains": null, "ukSpeech": null, "usSpeech": null}]}, "msg": "\u8bf7\u6c42\u6210\u529f\uff01"}