{"code": 200, "data": {"questionId": 3827, "questionType": 2, "typeName": "\u5355\u8bcd\u8fa8\u6790", "occurrence": 8, "isOccur": 0, "collectColorType": null, "practiceCount": 2, "createTime": "2020-11-13T07:47:00.000+00:00", "isVip": "1", "probationTotalCount": 0, "userProbationCountLeft": 0, "questionStatus": null, "ownerFlag": null, "similarToQuestionIdList": null, "title": "\u9009\u62e9\u6b63\u786e\u7684\u82f1\u8bed\u5355\u8bcd", "duration": 60, "difficulty": 2, "difficultyName": "\u4e00\u822c\uff08105~115\uff09", "options": [{"correct": 1, "word": "sufferer", "usPhonetic": "\u02c8s\u028cf\u0259r\u0259r", "ukPhonetic": "\u02c8s\u028cf\u0259r\u0259(r)", "explains": "[\"n. \u60a3\u8005\uff1b\u53d7\u5bb3\u8005\"]", "ukSpeech": "https://duolingo-prod.oss-cn-shanghai.aliyuncs.com/voices/480045917693546497.mp3", "usSpeech": "https://duolingo-prod.oss-cn-shanghai.aliyuncs.com/voices/480045917693546498.mp3"}, {"correct": 1, "word": "dedicate", "usPhonetic": "\u02c8ded\u026ake\u026at", "ukPhonetic": "\u02c8ded\u026ake\u026at", "explains": "[\"vt. \u81f4\u529b\uff1b\u732e\u8eab\uff1b\u9898\u732e\"]", "ukSpeech": "https://duolingo-prod.oss-cn-shanghai.aliyuncs.com/voices/480048352940003330.mp3", "usSpeech": "https://duolingo-prod.oss-cn-shanghai.aliyuncs.com/voices/480048357234970624.mp3"}, {"correct": 0, "word": "crassage", "usPhonetic": null, "ukPhonetic": null, "explains": null, "ukSpeech": null, "usSpeech": null}, {"correct": 0, "word": "incommunian", "usPhonetic": null, "ukPhonetic": null, "explains": null, "ukSpeech": null, "usSpeech": null}, {"correct": 0, "word": "snaterwear", "usPhonetic": null, "ukPhonetic": null, "explains": null, "ukSpeech": null, "usSpeech": null}, {"correct": 1, "word": "poorly", "usPhonetic": "\u02c8p\u028arli,\u02c8p\u0254\u02d0rli", "ukPhonetic": "\u02c8p\u0254\u02d0li; \u02c8p\u028a\u0259li", "explains": "[\"adv. \u8d2b\u7a77\u5730\uff1b\u8d2b\u4e4f\u5730\uff1b\u4e0d\u5145\u5206\u5730\",\"adj. \u8eab\u4f53\u4e0d\u8212\u670d\u7684\uff1b\u5fc3\u60c5\u6076\u52a3\u7684\"]", "ukSpeech": "https://duolingo-prod.oss-cn-shanghai.aliyuncs.com/voices/480045797434462211.mp3", "usSpeech": "https://duolingo-prod.oss-cn-shanghai.aliyuncs.com/voices/480045797434462212.mp3"}, {"correct": 0, "word": "brisp", "usPhonetic": null, "ukPhonetic": null, "explains": null, "ukSpeech": null, "usSpeech": null}, {"correct": 0, "word": "swiner", "usPhonetic": null, "ukPhonetic": null, "explains": null, "ukSpeech": null, "usSpeech": null}, {"correct": 0, "word": "infecutive", "usPhonetic": null, "ukPhonetic": null, "explains": null, "ukSpeech": null, "usSpeech": null}, {"correct": 0, "word": "schotalm", "usPhonetic": null, "ukPhonetic": null, "explains": null, "ukSpeech": null, "usSpeech": null}, {"correct": 0, "word": "broar", "usPhonetic": null, "ukPhonetic": null, "explains": null, "ukSpeech": null, "usSpeech": null}, {"correct": 1, "word": "bilingual", "usPhonetic": "\u02ccba\u026a\u02c8l\u026a\u014b\u0261w\u0259l", "ukPhonetic": "\u02ccba\u026a\u02c8l\u026a\u014b\u0261w\u0259l", "explains": "[\"adj. \u53cc\u8bed\u7684\",\"n. \u901a\u4e24\u79cd\u8bed\u8a00\u7684\u4eba\"]", "ukSpeech": "https://duolingo-prod.oss-cn-shanghai.aliyuncs.com/voices/480047953508044804.mp3", "usSpeech": "https://duolingo-prod.oss-cn-shanghai.aliyuncs.com/voices/480047953508044805.mp3"}, {"correct": 1, "word": "ironic", "usPhonetic": "a\u026a\u02c8r\u0251\u02d0n\u026ak", "ukPhonetic": "a\u026a\u02c8r\u0252n\u026ak", "explains": "[\"adj. \u8bbd\u523a\u7684\uff1b\u53cd\u8bdd\u7684\"]", "ukSpeech": "https://duolingo-prod.oss-cn-shanghai.aliyuncs.com/voices/480048292810461184.mp3", "usSpeech": "https://duolingo-prod.oss-cn-shanghai.aliyuncs.com/voices/480048292810461185.mp3"}, {"correct": 0, "word": "revonistance", "usPhonetic": null, "ukPhonetic": null, "explains": null, "ukSpeech": null, "usSpeech": null}, {"correct": 0, "word": "unjustical", "usPhonetic": null, "ukPhonetic": null, "explains": null, "ukSpeech": null, "usSpeech": null}, {"correct": 0, "word": "rewain", "usPhonetic": null, "ukPhonetic": null, "explains": null, "ukSpeech": null, "usSpeech": null}, {"correct": 1, "word": "recharge", "usPhonetic": "\u02ccri\u02d0\u02c8t\u0283\u0251\u02d0rd\u0292", "ukPhonetic": "\u02ccri\u02d0\u02c8t\u0283\u0251\u02d0d\u0292", "explains": "[\"vt. \u518d\u5145\u7535\uff1b\u518d\u88ad\u51fb\uff1b\u518d\u63a7\u544a\",\"n. \u518d\u88ad\u51fb\uff1b\u518d\u88c5\u586b\",\"vi. \u518d\u88ad\u51fb\"]", "ukSpeech": "https://duolingo-prod.oss-cn-shanghai.aliyuncs.com/voices/480046239816093699.mp3", "usSpeech": "https://duolingo-prod.oss-cn-shanghai.aliyuncs.com/voices/480046239816093700.mp3"}, {"correct": 0, "word": "presited", "usPhonetic": null, "ukPhonetic": null, "explains": null, "ukSpeech": null, "usSpeech": null}]}, "msg": "\u8bf7\u6c42\u6210\u529f\uff01"}