{"code": 200, "data": {"questionId": 3006, "questionType": 7, "typeName": "\u542c\u5199\u53e5\u5b50", "occurrence": 13, "isOccur": 0, "collectColorType": null, "practiceCount": 0, "createTime": "2020-11-12T18:06:00.000+00:00", "isVip": "1", "probationTotalCount": 0, "userProbationCountLeft": 0, "questionStatus": null, "ownerFlag": null, "similarToQuestionIdList": null, "title": "\u952e\u5165\u60a8\u542c\u5230\u7684\u5185\u5bb9", "duration": 60, "difficulty": 1, "difficultyName": "\u7b80\u5355\uff08100\u4ee5\u4e0b\uff09", "audio": "https://cdn.51ddedu.com/voices/477105063391662089.mp3", "answer": "I don't know anything about that.", "translate": "\u6211\u5bf9\u90a3\u4ef6\u4e8b\u4e00\u65e0\u6240\u77e5\u3002"}, "msg": "\u8bf7\u6c42\u6210\u529f\uff01"}