{"code": 200, "data": {"questionId": 7494, "questionType": 13, "typeName": "\u4e92\u52a8\u9605\u8bfb", "occurrence": 3, "isOccur": 0, "collectColorType": null, "practiceCount": 1, "createTime": "2022-12-09T03:32:51.532+00:00", "isVip": "1", "probationTotalCount": 0, "userProbationCountLeft": 0, "questionStatus": null, "ownerFlag": null, "similarToQuestionIdList": null, "difficulty": 3, "difficultyName": "\u96be\uff08120\u4ee5\u4e0a\uff09", "subQuestionId": 1, "duration": 420, "fullContent": "Metadata refers to data about data. Metadata helps to label, organize, and search data. It is used in databases, computer software, reports, documents, and other information-oriented items. Metadata helps to organize and categorize the information in the data to help with searching and referencing. Metadata may include properties about who created the data, its source, and usage restrictions. For instance, a school may include information about a lecturer's name and contact information, the name of the lecture series, the dates and times of the lectures, the type of medium that will be used to present the lecture (tape or CD), and other details.", "q1": {"type": 1, "markColorType": null, "translation": "\u5143\u6570\u636e\u662f\u5173\u4e8e\u6570\u636e\u7684\u6570\u636e\u3002\u5143\u6570\u636e\u6709\u52a9\u4e8e\u6807\u8bb0\u3001\u7ec4\u7ec7\u548c\u641c\u7d22\u6570\u636e\u3002\u5b83\u88ab\u7528\u4e8e\u6570\u636e\u5e93\u3001\u8ba1\u7b97\u673a\u8f6f\u4ef6\u3001\u62a5\u544a\u3001\u6587\u6863\u548c\u5176\u4ed6\u9762\u5411\u4fe1\u606f\u7684\u9879\u76ee\u3002\u5143\u6570\u636e\u6709\u52a9\u4e8e\u7ec4\u7ec7\u548c\u5206\u7c7b\u6570\u636e\u4e2d\u7684\u4fe1\u606f\uff0c\u4ee5\u5e2e\u52a9\u641c\u7d22\u548c\u5f15\u7528\u3002", "status": 1, "deleted": 0, "front": "Metadata refers to data about data. Metadata helps to label, organize, and search data. It is used in databases, computer software, reports, documents, and other information-oriented items. Metadata helps to organize and categorize the information in the data to help with searching and referencing.", "content": "Metadata ____ to data about data. Metadata helps to label, organize, and search ____. It is ____ in databases, computer software, reports, documents, and other information-oriented items. Metadata helps to organize and categorize the ____ in the data to ____ with searching and referencing.", "options": [["belongs", "according", "helps", "refers", "related"], ["labels", "structures", "data", "reports", "artifacts"], ["presented", "written", "displayed", "expressed", "used"], ["information", "change", "words", "symbols", "features"], ["facilitate", "help", "do", "interfere", "experiment"]], "answer": ["refers", "data", "used", "information", "help"]}, "q2": {"type": 2, "markColorType": null, "translation": "\u5143\u6570\u636e\u662f\u5173\u4e8e\u6570\u636e\u7684\u6570\u636e\u3002\u5143\u6570\u636e\u6709\u52a9\u4e8e\u6807\u8bb0\u3001\u7ec4\u7ec7\u548c\u641c\u7d22\u6570\u636e\u3002\u5b83\u88ab\u7528\u4e8e\u6570\u636e\u5e93\u3001\u8ba1\u7b97\u673a\u8f6f\u4ef6\u3001\u62a5\u544a\u3001\u6587\u6863\u548c\u5176\u4ed6\u9762\u5411\u4fe1\u606f\u7684\u9879\u76ee\u3002\u5143\u6570\u636e\u6709\u52a9\u4e8e\u7ec4\u7ec7\u548c\u5206\u7c7b\u6570\u636e\u4e2d\u7684\u4fe1\u606f\uff0c\u4ee5\u5e2e\u52a9\u641c\u7d22\u548c\u5f15\u7528\u3002\u5143\u6570\u636e\u53ef\u80fd\u5305\u62ec\u5173\u4e8e\u8c01\u521b\u5efa\u4e86\u6570\u636e\u3001\u6570\u636e\u6765\u6e90\u548c\u4f7f\u7528\u9650\u5236\u7684\u5c5e\u6027\u3002\u4f8b\u5982\uff0c\u5b66\u6821\u53ef\u80fd\u5305\u62ec\u8bb2\u5e08\u7684\u59d3\u540d\u548c\u8054\u7cfb\u65b9\u5f0f\u3001\u7cfb\u5217\u8bb2\u5ea7\u7684\u540d\u79f0\u3001\u8bb2\u5ea7\u7684\u65e5\u671f\u548c\u65f6\u95f4\u3001\u5c06\u7528\u4e8e\u6f14\u793a\u8bb2\u5ea7\u7684\u5a92\u4ecb\u7c7b\u578b(\u78c1\u5e26\u6216CD)\u4ee5\u53ca\u5176\u4ed6\u8be6\u7ec6\u4fe1\u606f\u3002", "status": 1, "deleted": 0, "front": "Metadata refers to data about data. Metadata helps to label, organize, and search data. It is used in databases, computer software, reports, documents, and other information-oriented items. Metadata helps to organize and categorize the information in the data to help with searching and referencing.", "middle": "Metadata may include properties about who created the data, its source, and usage restrictions.", "ending": "For instance, a school may include information about a lecturer's name and contact information, the name of the lecture series, the dates and times of the lectures, the type of medium that will be used to present the lecture (tape or CD), and other details.", "options": [{"sentence": "But storing information in our brains via long-term memory requires information processing.", "correct": 0}, {"sentence": "Information science principles are also applied to other fields in the social sciences.", "correct": 0}, {"sentence": "Metadata may include properties about who created the data, its source, and usage restrictions.", "correct": 1}, {"sentence": "Information scientists help businesses and governments make decisions based on available data.", "correct": 0}]}, "q3": {"type": 3, "markColorType": null, "translation": "\u5143\u6570\u636e\u662f\u5173\u4e8e\u6570\u636e\u7684\u6570\u636e\u3002\u5143\u6570\u636e\u6709\u52a9\u4e8e\u6807\u8bb0\u3001\u7ec4\u7ec7\u548c\u641c\u7d22\u6570\u636e\u3002\u5b83\u88ab\u7528\u4e8e\u6570\u636e\u5e93\u3001\u8ba1\u7b97\u673a\u8f6f\u4ef6\u3001\u62a5\u544a\u3001\u6587\u6863\u548c\u5176\u4ed6\u9762\u5411\u4fe1\u606f\u7684\u9879\u76ee\u3002\u5143\u6570\u636e\u6709\u52a9\u4e8e\u7ec4\u7ec7\u548c\u5206\u7c7b\u6570\u636e\u4e2d\u7684\u4fe1\u606f\uff0c\u4ee5\u5e2e\u52a9\u641c\u7d22\u548c\u5f15\u7528\u3002\u5143\u6570\u636e\u53ef\u80fd\u5305\u62ec\u5173\u4e8e\u8c01\u521b\u5efa\u4e86\u6570\u636e\u3001\u6570\u636e\u6765\u6e90\u548c\u4f7f\u7528\u9650\u5236\u7684\u5c5e\u6027\u3002\u4f8b\u5982\uff0c\u5b66\u6821\u53ef\u80fd\u5305\u62ec\u8bb2\u5e08\u7684\u59d3\u540d\u548c\u8054\u7cfb\u65b9\u5f0f\u3001\u7cfb\u5217\u8bb2\u5ea7\u7684\u540d\u79f0\u3001\u8bb2\u5ea7\u7684\u65e5\u671f\u548c\u65f6\u95f4\u3001\u5c06\u7528\u4e8e\u6f14\u793a\u8bb2\u5ea7\u7684\u5a92\u4ecb\u7c7b\u578b(\u78c1\u5e26\u6216CD)\u4ee5\u53ca\u5176\u4ed6\u8be6\u7ec6\u4fe1\u606f\u3002", "status": 1, "deleted": 0, "content": "Metadata refers to data about data. Metadata helps to label, organize, and search data. It is used in databases, computer software, reports, documents, and other information-oriented items. Metadata helps to organize and categorize the information in the data to help with searching and referencing. Metadata may include properties about who created the data, its source, and usage restrictions. For instance, a school may include information about a lecturer's name and contact information, the name of the lecture series, the dates and times of the lectures, the type of medium that will be used to present the lecture (tape or CD), and other details.", "questionContent": "What is the main purpose of metadata?", "selectAnswer": "Metadata helps to label, organize, and search data", "answerIntroduction": null}, "q4": {"type": 3, "markColorType": null, "translation": "\u5143\u6570\u636e\u662f\u5173\u4e8e\u6570\u636e\u7684\u6570\u636e\u3002\u5143\u6570\u636e\u6709\u52a9\u4e8e\u6807\u8bb0\u3001\u7ec4\u7ec7\u548c\u641c\u7d22\u6570\u636e\u3002\u5b83\u88ab\u7528\u4e8e\u6570\u636e\u5e93\u3001\u8ba1\u7b97\u673a\u8f6f\u4ef6\u3001\u62a5\u544a\u3001\u6587\u6863\u548c\u5176\u4ed6\u9762\u5411\u4fe1\u606f\u7684\u9879\u76ee\u3002\u5143\u6570\u636e\u6709\u52a9\u4e8e\u7ec4\u7ec7\u548c\u5206\u7c7b\u6570\u636e\u4e2d\u7684\u4fe1\u606f\uff0c\u4ee5\u5e2e\u52a9\u641c\u7d22\u548c\u5f15\u7528\u3002\u5143\u6570\u636e\u53ef\u80fd\u5305\u62ec\u5173\u4e8e\u8c01\u521b\u5efa\u4e86\u6570\u636e\u3001\u6570\u636e\u6765\u6e90\u548c\u4f7f\u7528\u9650\u5236\u7684\u5c5e\u6027\u3002\u4f8b\u5982\uff0c\u5b66\u6821\u53ef\u80fd\u5305\u62ec\u8bb2\u5e08\u7684\u59d3\u540d\u548c\u8054\u7cfb\u65b9\u5f0f\u3001\u7cfb\u5217\u8bb2\u5ea7\u7684\u540d\u79f0\u3001\u8bb2\u5ea7\u7684\u65e5\u671f\u548c\u65f6\u95f4\u3001\u5c06\u7528\u4e8e\u6f14\u793a\u8bb2\u5ea7\u7684\u5a92\u4ecb\u7c7b\u578b(\u78c1\u5e26\u6216CD)\u4ee5\u53ca\u5176\u4ed6\u8be6\u7ec6\u4fe1\u606f\u3002", "status": 1, "deleted": 0, "content": "Metadata refers to data about data. Metadata helps to label, organize, and search data. It is used in databases, computer software, reports, documents, and other information-oriented items. Metadata helps to organize and categorize the information in the data to help with searching and referencing. Metadata may include properties about who created the data, its source, and usage restrictions. For instance, a school may include information about a lecturer's name and contact information, the name of the lecture series, the dates and times of the lectures, the type of medium that will be used to present the lecture (tape or CD), and other details.", "questionContent": "What are some examples of metadata properties?", "selectAnswer": "a school may include information about a lecturer's name and contact information, the name of the lecture series, the dates and times of the lectures, the type of medium that will be used to present the lecture (tape or CD), and other details.", "answerIntroduction": null}, "q5": {"type": 4, "markColorType": null, "translation": "\u5143\u6570\u636e\u662f\u5173\u4e8e\u6570\u636e\u7684\u6570\u636e\u3002\u5143\u6570\u636e\u6709\u52a9\u4e8e\u6807\u8bb0\u3001\u7ec4\u7ec7\u548c\u641c\u7d22\u6570\u636e\u3002\u5b83\u88ab\u7528\u4e8e\u6570\u636e\u5e93\u3001\u8ba1\u7b97\u673a\u8f6f\u4ef6\u3001\u62a5\u544a\u3001\u6587\u6863\u548c\u5176\u4ed6\u9762\u5411\u4fe1\u606f\u7684\u9879\u76ee\u3002\u5143\u6570\u636e\u6709\u52a9\u4e8e\u7ec4\u7ec7\u548c\u5206\u7c7b\u6570\u636e\u4e2d\u7684\u4fe1\u606f\uff0c\u4ee5\u5e2e\u52a9\u641c\u7d22\u548c\u5f15\u7528\u3002\u5143\u6570\u636e\u53ef\u80fd\u5305\u62ec\u5173\u4e8e\u8c01\u521b\u5efa\u4e86\u6570\u636e\u3001\u6570\u636e\u6765\u6e90\u548c\u4f7f\u7528\u9650\u5236\u7684\u5c5e\u6027\u3002\u4f8b\u5982\uff0c\u5b66\u6821\u53ef\u80fd\u5305\u62ec\u8bb2\u5e08\u7684\u59d3\u540d\u548c\u8054\u7cfb\u65b9\u5f0f\u3001\u7cfb\u5217\u8bb2\u5ea7\u7684\u540d\u79f0\u3001\u8bb2\u5ea7\u7684\u65e5\u671f\u548c\u65f6\u95f4\u3001\u5c06\u7528\u4e8e\u6f14\u793a\u8bb2\u5ea7\u7684\u5a92\u4ecb\u7c7b\u578b(\u78c1\u5e26\u6216CD)\u4ee5\u53ca\u5176\u4ed6\u8be6\u7ec6\u4fe1\u606f\u3002", "status": 1, "deleted": 0, "content": "Metadata refers to data about data. Metadata helps to label, organize, and search data. It is used in databases, computer software, reports, documents, and other information-oriented items. Metadata helps to organize and categorize the information in the data to help with searching and referencing. Metadata may include properties about who created the data, its source, and usage restrictions. For instance, a school may include information about a lecturer's name and contact information, the name of the lecture series, the dates and times of the lectures, the type of medium that will be used to present the lecture (tape or CD), and other details.", "options": [{"sentence": "Data mining is the search for anomalies and correlations within large data sets.", "correct": 0}, {"sentence": "Classification uses machine learning and pattern recognition to identify and classify objects and relationships.", "correct": 0}, {"sentence": "Clustering, also known as social network analysis, studies groupings of objects based on common characteristics.", "correct": 0}, {"sentence": "Metadata helps to organize and label other data using information about the data.", "correct": 1}]}, "q6": {"type": 5, "markColorType": null, "translation": "\u5143\u6570\u636e\u662f\u5173\u4e8e\u6570\u636e\u7684\u6570\u636e\u3002\u5143\u6570\u636e\u6709\u52a9\u4e8e\u6807\u8bb0\u3001\u7ec4\u7ec7\u548c\u641c\u7d22\u6570\u636e\u3002\u5b83\u88ab\u7528\u4e8e\u6570\u636e\u5e93\u3001\u8ba1\u7b97\u673a\u8f6f\u4ef6\u3001\u62a5\u544a\u3001\u6587\u6863\u548c\u5176\u4ed6\u9762\u5411\u4fe1\u606f\u7684\u9879\u76ee\u3002\u5143\u6570\u636e\u6709\u52a9\u4e8e\u7ec4\u7ec7\u548c\u5206\u7c7b\u6570\u636e\u4e2d\u7684\u4fe1\u606f\uff0c\u4ee5\u5e2e\u52a9\u641c\u7d22\u548c\u5f15\u7528\u3002\u5143\u6570\u636e\u53ef\u80fd\u5305\u62ec\u5173\u4e8e\u8c01\u521b\u5efa\u4e86\u6570\u636e\u3001\u6570\u636e\u6765\u6e90\u548c\u4f7f\u7528\u9650\u5236\u7684\u5c5e\u6027\u3002\u4f8b\u5982\uff0c\u5b66\u6821\u53ef\u80fd\u5305\u62ec\u8bb2\u5e08\u7684\u59d3\u540d\u548c\u8054\u7cfb\u65b9\u5f0f\u3001\u7cfb\u5217\u8bb2\u5ea7\u7684\u540d\u79f0\u3001\u8bb2\u5ea7\u7684\u65e5\u671f\u548c\u65f6\u95f4\u3001\u5c06\u7528\u4e8e\u6f14\u793a\u8bb2\u5ea7\u7684\u5a92\u4ecb\u7c7b\u578b(\u78c1\u5e26\u6216CD)\u4ee5\u53ca\u5176\u4ed6\u8be6\u7ec6\u4fe1\u606f\u3002", "status": 1, "deleted": 0, "content": "Metadata refers to data about data. Metadata helps to label, organize, and search data. It is used in databases, computer software, reports, documents, and other information-oriented items. Metadata helps to organize and categorize the information in the data to help with searching and referencing. Metadata may include properties about who created the data, its source, and usage restrictions. For instance, a school may include information about a lecturer's name and contact information, the name of the lecture series, the dates and times of the lectures, the type of medium that will be used to present the lecture (tape or CD), and other details.", "options": [{"sentence": "Data Forms and Data Entry", "correct": 0}, {"sentence": "Computers, Science, and Ethics", "correct": 0}, {"sentence": "Introduction to Metadata", "correct": 1}, {"sentence": "Thinking with Data", "correct": 0}]}}, "msg": "\u8bf7\u6c42\u6210\u529f\uff01"}