{"code": 200, "data": {"questionId": 2512, "questionType": 8, "typeName": "\u5355\u8bcd\u586b\u7a7a", "occurrence": 19, "isOccur": 0, "collectColorType": null, "practiceCount": 1, "createTime": "2020-11-12T09:52:00.000+00:00", "isVip": "1", "probationTotalCount": 0, "userProbationCountLeft": 0, "questionStatus": null, "ownerFlag": null, "similarToQuestionIdList": null, "title": "\u952e\u5165\u7f3a\u5c11\u7684\u5b57\u6bcd\uff0c\u5b8c\u6210\u4e0b\u9762\u7684\u6587\u5b57", "duration": 180, "difficulty": 1, "difficultyName": "\u7b80\u5355\uff08100\u4ee5\u4e0b\uff09", "blankContent": "One warm summer night, Angela went to a festival in her neighborhood. Bands ____ playing, and ____ people ____ happily ____ to ____ music. Angela ____ along ____ streets ____ the ____, ____ looked ____ all ____ goods ____ were ____. After seeing everything, she bought a new sun hat.", "partBlankContent": "One warm summer night, Angela went to a festival in her neighborhood. Bands we__ playing, and ma__ people we__ happily dan____ to t__ music. Angela wal___ along t__ streets o_ the fest____, a__ looked a_ all t__ goods peo___ were sel____. After seeing everything, she bought a new sun hat.", "fullContent": "\nOne warm summer night, Angela went to a festival in her neighborhood. Bands were playing, and many people were happily dancing to the music. Angela walked along the streets of the festival, and looked at all the goods people were selling. After seeing everything, she bought a new sun hat.", "answer": "\u4e00\u4e2a\u6e29\u6696\u7684\u590f\u591c\uff0c\u5b89\u742a\u62c9\u53bb\u53c2\u52a0\u5979\u6240\u5728\u793e\u533a\u7684\u4e00\u4e2a\u8282\u65e5\u3002\u4e50\u961f\u5728\u6f14\u594f\uff0c\u7fa4\u4f17\u548c\u7740\u97f3\u4e50\u9ad8\u5174\u5730\u8df3\u821e\u3002\u5b89\u5409\u62c9\u6cbf\u7740\u8282\u65e5\u7684\u8857\u9053\u8d70\u7740\uff0c\u770b\u7740\u4eba\u4eec\u5728\u5356\u7684\u6240\u6709\u5546\u54c1\u3002\u770b\u5b8c\u6240\u6709\u7684\u4e1c\u897f\u540e\uff0c\u5979\u4e70\u4e86\u4e00\u9876\u65b0\u7684\u592a\u9633\u5e3d\u3002", "options": [{"letterSize": 2, "word": "were"}, {"letterSize": 2, "word": "many"}, {"letterSize": 2, "word": "were"}, {"letterSize": 3, "word": "dancing"}, {"letterSize": 1, "word": "the"}, {"letterSize": 3, "word": "walked"}, {"letterSize": 1, "word": "the"}, {"letterSize": 1, "word": "of"}, {"letterSize": 4, "word": "festival"}, {"letterSize": 1, "word": "and"}, {"letterSize": 1, "word": "at"}, {"letterSize": 1, "word": "the"}, {"letterSize": 3, "word": "people"}, {"letterSize": 3, "word": "selling"}]}, "msg": "\u8bf7\u6c42\u6210\u529f\uff01"}