{"code": 200, "data": {"questionId": 4683, "questionType": 8, "typeName": "\u5355\u8bcd\u586b\u7a7a", "occurrence": 4, "isOccur": 0, "collectColorType": null, "practiceCount": 0, "createTime": "2020-11-13T22:03:00.000+00:00", "isVip": "1", "probationTotalCount": 0, "userProbationCountLeft": 0, "questionStatus": null, "ownerFlag": null, "similarToQuestionIdList": null, "title": "\u952e\u5165\u7f3a\u5c11\u7684\u5b57\u6bcd\uff0c\u5b8c\u6210\u4e0b\u9762\u7684\u6587\u5b57", "duration": 180, "difficulty": 2, "difficultyName": "\u4e00\u822c\uff08105~115\uff09", "blankContent": "These specifications seem off somehow. We're ____ to ____ these ____ of ____ using ____ nails ____ in ____ kit. But I measured ____, ____ there's a mismatch ____ the ____ and ____ size ____ the ____. Could we be working from the wrong instructions, or do we need to modify them somehow?", "partBlankContent": "These specifications seem off somehow. We're supp____ to jo__ these pie___ of wo__ using t__ nails prov____ in t__ kit. But I measured th__, a__ there's a mismatch bet____ the na___ and t__ size o_ the ho___. Could we be working from the wrong instructions, or do we need to modify them somehow?", "fullContent": "\nThese specifications seem off somehow. We're supposed to join these pieces of wood using the nails provided in the kit. But I measured them, and there's a mismatch between the nails and the size of the holes. Could we be working from the wrong instructions, or do we need to modify them somehow?", "answer": "\u4e0d\u77e5\u600e\u4e48\u7684\uff0c\u8fd9\u4e9b\u8bf4\u660e\u4f3c\u4e4e\u4e0d\u592a\u6b63\u786e\u3002\u6211\u4eec\u5e94\u8be5\u7528\u5de5\u5177\u7bb1\u91cc\u63d0\u4f9b\u7684\u9489\u5b50\u628a\u8fd9\u4e9b\u6728\u5934\u8fde\u63a5\u8d77\u6765\u3002\u4f46\u6211\u6d4b\u91cf\u8fc7\u4e86\uff0c\u9489\u5b50\u548c\u6d1e\u7684\u5927\u5c0f\u4e0d\u4e00\u81f4\u3002\u6211\u4eec\u662f\u6839\u636e\u9519\u8bef\u7684\u6307\u4ee4\u5de5\u4f5c\uff0c\u8fd8\u662f\u6211\u4eec\u9700\u8981\u4fee\u6539\u5b83\u4eec?", "options": [{"letterSize": 4, "word": "supposed"}, {"letterSize": 2, "word": "join"}, {"letterSize": 3, "word": "pieces"}, {"letterSize": 2, "word": "wood"}, {"letterSize": 1, "word": "the"}, {"letterSize": 4, "word": "provided"}, {"letterSize": 1, "word": "the"}, {"letterSize": 2, "word": "them"}, {"letterSize": 1, "word": "and"}, {"letterSize": 3, "word": "between"}, {"letterSize": 2, "word": "nails"}, {"letterSize": 1, "word": "the"}, {"letterSize": 1, "word": "of"}, {"letterSize": 2, "word": "holes"}]}, "msg": "\u8bf7\u6c42\u6210\u529f\uff01"}