{"code": 200, "data": {"questionId": 7029, "questionType": 5, "typeName": "\u542c\u9898\u6f14\u8bb2", "occurrence": 4, "isOccur": 0, "collectColorType": null, "practiceCount": 0, "createTime": "2022-08-10T04:30:00.461+00:00", "isVip": "1", "probationTotalCount": 0, "userProbationCountLeft": 0, "questionStatus": null, "ownerFlag": null, "similarToQuestionIdList": null, "title": "\u51c6\u5907\u4ee5\u81f3\u5c1120\u79d2\u7684\u65f6\u95f4\u56de\u7b54\u4ee5\u4e0b\u95ee\u9898", "duration": 90, "prepareTime": 20, "templateType": 2, "templateName": "\u89e3\u51b3\u7c7b\u6a21\u677f", "audio": "https://cdn.51ddedu.com/voices/624358536826068992.mp3", "answer": "There are a lot of ways for schools and communities to promote healthy habits in children and adolescents. First of all, schools can have classes specifically designed to teach children what healthy habits they need to have. Secondly, teachers should pay attention to children's healthy habits when they are at school. Adults in local communities should be role models by doing the right thing when it comes to personal hygiene. For example, washing hands frequently is very important to prevent diseases from spreading. Overall, it is essential for schools and communities to disseminate the message that healthy habits are important.", "referenceText": "How can schools and communities promote healthy habits in children and adolescents?", "referenceTranslate": "\u5b66\u6821\u548c\u793e\u533a\u5982\u4f55\u4fc3\u8fdb\u513f\u7ae5\u548c\u9752\u5c11\u5e74\u7684\u5065\u5eb7\u4e60\u60ef?", "difficulty": 2, "difficultyName": "\u4e00\u822c\uff08105~115\uff09"}, "msg": "\u8bf7\u6c42\u6210\u529f\uff01"}